fastapi_refine/__init__.py
fastapi_refine/py.typed
fastapi_refine/core/__init__.py
fastapi_refine/core/query.py
fastapi_refine/core/types.py
fastapi_refine/dependencies/__init__.py
fastapi_refine/dependencies/query.py
fastapi_refine/dependencies/response.py
fastapi_refine/hooks/__init__.py
fastapi_refine/hooks/base.py
fastapi_refine/hooks/builtin.py
fastapi_refine/routers/__init__.py
fastapi_refine/routers/factory.py
fastapi_refine/utils/__init__.py
fastapi_refine-0.1.0.dist-info/METADATA
fastapi_refine-0.1.0.dist-info/WHEEL
fastapi_refine-0.1.0.dist-info/licenses/LICENSE
fastapi_refine-0.1.0.dist-info/RECORD
