Metadata-Version: 2.4
Name: fastapi-refine
Version: 0.1.0
Summary: FastAPI integration for Refine simple-rest data provider
Project-URL: Homepage, https://github.com/koch3092/fastapi-refine
Project-URL: Documentation, https://github.com/koch3092/fastapi-refine#readme
Project-URL: Repository, https://github.com/koch3092/fastapi-refine
Project-URL: Bug Tracker, https://github.com/koch3092/fastapi-refine/issues
Author-email: koko <developer@dorakoch.com>
License: MIT
License-File: LICENSE
Keywords: crud,fastapi,refine,rest,sqlalchemy,sqlmodel
Classifier: Development Status :: 3 - Alpha
Classifier: Framework :: FastAPI
Classifier: Intended Audience :: Developers
Classifier: License :: OSI Approved :: MIT License
Classifier: Programming Language :: Python :: 3
Classifier: Programming Language :: Python :: 3.10
Classifier: Programming Language :: Python :: 3.11
Classifier: Programming Language :: Python :: 3.12
Classifier: Programming Language :: Python :: 3.13
Classifier: Topic :: Internet :: WWW/HTTP
Classifier: Topic :: Software Development :: Libraries :: Python Modules
Classifier: Typing :: Typed
Requires-Python: >=3.10
Requires-Dist: fastapi>=0.114.2
Requires-Dist: sqlmodel>=0.0.21
Provides-Extra: dev
Requires-Dist: mypy>=1.8.0; extra == 'dev'
Requires-Dist: pytest>=7.4.3; extra == 'dev'
Requires-Dist: ruff>=0.2.2; extra == 'dev'
